smecv_grid/__init__.py
smecv_grid/grid.py
smecv_grid/definition_files/ESA-CCI-SOILMOISTURE-LAND_AND_RAINFOREST_MASK-fv04.2.nc
smecv_grid/definition_files/ESA-CCI-SOILMOISTURE-LAND_AND_RAINFOREST_MASK-fv05.2.nc
smecv_grid/definition_files/ESA-CCI-SOILMOISTURE-LAND_AND_RAINFOREST_MASK-fvMR01.0.nc
smecv_grid-0.6.dist-info/licenses/AUTHORS.rst
smecv_grid-0.6.dist-info/licenses/LICENSE.txt
smecv_grid-0.6.dist-info/METADATA
smecv_grid-0.6.dist-info/WHEEL
smecv_grid-0.6.dist-info/top_level.txt
smecv_grid-0.6.dist-info/RECORD
