Metadata-Version: 2.4
Name: smecv_grid
Version: 0.6
Summary: Grid definition of the Discrete Global Grid (DGG) for ESA CCI SM and C3S SM.
Author-email: TU Wien <support@qa4sm.eu>
License: mit
Project-URL: Documentation, https://smecv-grid.readthedocs.io/en/latest/?badge=latest
Classifier: Development Status :: 4 - Beta
Classifier: Programming Language :: Python
Classifier: License :: OSI Approved :: MIT License
Classifier: Operating System :: OS Independent
Requires-Python: >=3.6
License-File: LICENSE.txt
License-File: AUTHORS.rst
Requires-Dist: numpy
Requires-Dist: netCDF4
Requires-Dist: pykdtree
Requires-Dist: configparser
Requires-Dist: pygeogrids
Requires-Dist: pyproj
Requires-Dist: more_itertools
Provides-Extra: building
Requires-Dist: setuptools>=46.1.0; extra == "building"
Requires-Dist: setuptools_scm[toml]>=5; extra == "building"
Requires-Dist: wheel; extra == "building"
Requires-Dist: packaging; extra == "building"
Requires-Dist: build; extra == "building"
Requires-Dist: twine; extra == "building"
Provides-Extra: testing
Requires-Dist: pytest; extra == "testing"
Requires-Dist: pytest-cov; extra == "testing"
Dynamic: license-file
